{
    "version": "0.3.7.1",
    "license": "GPL-3.0",
    "url": "https://github.com/oyvindln/vhs-decode/releases/download/0.3.7.1/decode_suite_full_v0.3.7_windows_x86_64.zip",
    "homepage": "https://github.com/oyvindln/vhs-decode/",
    "hash": "5cbddb2da93501aeca7b7744de248e29ed5e835d4ec4a4acad7ae360fb01e672",
    "bin": [
        "decode/AutoAudioAlign.exe",
        "decode/CUETools.FLACCL.cmd.exe",
        "decode/decode.exe",
        "decode/efm-decoder-audio.exe",
        "decode/efm-decoder-d24.exe",
        "decode/efm-decoder-data.exe",
        "decode/efm-decoder-f2.exe",
        "decode/efm-stacker-f2.exe",
        "decode/ld-ac3-decode.exe",
        "decode/ld-ac3-demodulate.exe",
        "decode/ld-analyse.exe",
        "decode/ld-chroma-decoder.exe",
        "decode/ld-chroma-encoder.exe",
        "decode/ld-disc-stacker.exe",
        "decode/ld-discmap.exe",
        "decode/ld-dropout-correct.exe",
        "decode/ld-export-metadata.exe",
        "decode/ld-ldf-reader.exe",
        "decode/ld-lds-converter.exe",
        "decode/ld-process-efm.exe",
        "decode/ld-process-vbi.exe",
        "decode/ld-process-vits.exe",
        "decode/lds-compress-nvidia-gpu.bat",
        "decode/lds-compress.bat",
        "decode/lds-unpack.bat",
        "decode/metaflac.exe",
        "decode/ntsc_proxy.bat",
        "decode/pal_proxy.bat",
        "decode/pcm-to-wav.bat",
        "decode/proxy.bat",
        "decode/s16-to-flac.bat",
        "decode/tbc-dropout-correct.bat",
        "decode/tbc-process-vbi.bat",
        "decode/tbc-video-export.exe",
        "decode/u8-to-flac.bat",
        "decode/vfs-verifier.exe"
    ]
}
